pelican_just_table/__init__.py
pelican_just_table/just_table.py
pelican_just_table-0.1.0.dist-info/LICENSE
pelican_just_table-0.1.0.dist-info/WHEEL
pelican_just_table-0.1.0.dist-info/METADATA
pelican_just_table-0.1.0.dist-info/RECORD
